make_certs/__init__.py
make_certs/certificate.py
make_certs/certificate_revokation_list.py
make_certs/exceptions.py
make_certs/main.py
make_certs/private_key.py
make_certs/utils.py
make_certs-0.2.1.dist-info/LICENSE.md
make_certs-0.2.1.dist-info/METADATA
make_certs-0.2.1.dist-info/WHEEL
make_certs-0.2.1.dist-info/entry_points.txt
make_certs-0.2.1.dist-info/top_level.txt
make_certs-0.2.1.dist-info/RECORD
