Metadata-Version: 2.1
Name: make-certs
Version: 0.2.1
Summary: Create simple hierarhy of x509 certificates
Classifier: Topic :: System :: Systems Administration
Classifier: License :: CC0 1.0 Universal (CC0 1.0) Public Domain Dedication
Requires-Python: >=3.10
License-File: LICENSE.md
Requires-Dist: cryptography>=35
Requires-Dist: pyyaml
